business_logic/__init__.py
business_logic/core.py
business_logic/errors.py
business_logic/exceptions.py
business_logic/tests.py
python_business_logic-0.2.0.dist-info/DESCRIPTION.rst
python_business_logic-0.2.0.dist-info/METADATA
python_business_logic-0.2.0.dist-info/RECORD
python_business_logic-0.2.0.dist-info/WHEEL
python_business_logic-0.2.0.dist-info/metadata.json
python_business_logic-0.2.0.dist-info/top_level.txt
