Metadata-Version: 2.0
Name: python-business-logic
Version: 0.2.0
Summary: Python package that makes creating complicated business logic easy
Home-page: https://github.com/Valian/python-business-logic
Author: Jakub Skałecki
Author-email: jakub.skalecki@gmail.com
License: MIT
Keywords: python-business-logic
Platform: UNKNOWN
Classifier: Development Status :: 3 - Alpha
Classifier: Intended Audience :: Developers
Classifier: License :: OSI Approved :: BSD License
Classifier: Natural Language :: English
Classifier: Programming Language :: Python :: 2
Classifier: Programming Language :: Python :: 2.7
Classifier: Programming Language :: Python :: 3
Classifier: Programming Language :: Python :: 3.3
Classifier: Programming Language :: Python :: 3.4
Classifier: Programming Language :: Python :: 3.5
Classifier: Programming Language :: Python :: 3.6
Classifier: Programming Language :: Python :: 3.7
Requires-Dist: six
